nonebot_desktop_wing/__init__.py
nonebot_desktop_wing/constants.py
nonebot_desktop_wing/hindsight.py
nonebot_desktop_wing/lazylib.py
nonebot_desktop_wing/lazylib.pyi
nonebot_desktop_wing/molecules.py
nonebot_desktop_wing/project.py
nonebot_desktop_wing/resources.py
nonebot_desktop_wing-0.2.8.dist-info/LICENSE
nonebot_desktop_wing-0.2.8.dist-info/METADATA
nonebot_desktop_wing-0.2.8.dist-info/WHEEL
nonebot_desktop_wing-0.2.8.dist-info/top_level.txt
nonebot_desktop_wing-0.2.8.dist-info/RECORD
