Metadata-Version: 2.1
Name: nonebot-desktop-wing
Version: 0.2.8
Summary: Wings for NoneBot desktop applications.
Author-email: HivertMoZara <worldmozara@163.com>
License: MIT
Project-URL: Homepage, https://github.com/nonedesktop/nonebot-desktop-wing
Project-URL: Repository, https://github.com/nonedesktop/nonebot-desktop-wing
Requires-Python: >=3.8
License-File: LICENSE
Requires-Dist: nb-cli (~=1.0.0)
Requires-Dist: python-dotenv (~=1.0.0)
Requires-Dist: httpx (>=0.23)
Requires-Dist: typing-extensions (>=4.5.0)
